{"cameraMode":{"drawMode":0,"name":"Shaded","section":"Shading Mode"},"sceneLighting":true,"audioPlay":false,"sceneViewState":{"m_AlwaysRefresh":false,"showFog":true,"showSkybox":true,"showFlares":true,"showImageEffects":true,"showParticleSystems":true,"showVisualEffectGraphs":true,"m_FxEnabled":true},"in2DMode":false,"pivot":{"x":-0.014429304748773575,"y":0.16501843929290772,"z":-5.835154056549072},"rotation":{"x":0.1345849186182022,"y":-0.008918039500713349,"z":0.001211310620419681,"w":0.990861713886261},"size":1.9192230701446534,"orthographic":false}